{
	"configurations" : 
	[
		{
			"directories" : 
			[
				{
					"build" : ".",
					"jsonFile" : "directory-.-Debug-f5ebdc15457944623624.json",
					"minimumCMakeVersion" : 
					{
						"string" : "3.24"
					},
					"projectIndex" : 0,
					"source" : ".",
					"targetIndexes" : 
					[
						0
					]
				}
			],
			"name" : "Debug",
			"projects" : 
			[
				{
					"directoryIndexes" : 
					[
						0
					],
					"name" : "Chapter2",
					"targetIndexes" : 
					[
						0
					]
				}
			],
			"targets" : 
			[
				{
					"directoryIndex" : 0,
					"id" : "Chapter2::@6890427a1f51a3e7e1df",
					"jsonFile" : "target-Chapter2-Debug-ccb3a46b40d06b256369.json",
					"name" : "Chapter2",
					"projectIndex" : 0
				}
			]
		}
	],
	"kind" : "codemodel",
	"paths" : 
	{
		"build" : "/Users/luoruidi/Desktop/C++ Note/C++Learn/C++\u7b2c\u4e00\u90e8\u5206/Chapter2/cmake-build-debug",
		"source" : "/Users/luoruidi/Desktop/C++ Note/C++Learn/C++\u7b2c\u4e00\u90e8\u5206/Chapter2"
	},
	"version" : 
	{
		"major" : 2,
		"minor" : 4
	}
}
